py_lex/__init__.py
py_lex/emo_lex.py
py_lex/liwc.py
py_lex/liwc_parser.py
py_lex/nrc_discrete_parser.py
py_lex-0.2.1.dist-info/DESCRIPTION.rst
py_lex-0.2.1.dist-info/METADATA
py_lex-0.2.1.dist-info/RECORD
py_lex-0.2.1.dist-info/WHEEL
py_lex-0.2.1.dist-info/metadata.json
py_lex-0.2.1.dist-info/top_level.txt
