Metadata-Version: 2.0
Name: py-lex
Version: 0.2.1
Summary: UNKNOWN
Home-page: https://github.com/dropofwill/py-lex
Author: Will Paul
Author-email: whp3652@rit.edu
License: UNKNOWN
Platform: UNKNOWN
Requires-Dist: bidict (>=0.11)
Requires-Dist: marisa-trie (>=0.7)
